Workbook

Sheet Menu
B1: AGREGADOR DE DADOS PARA O IMPOSTO DE RENDA
B4: Organize rendimentos, despesas, bens e documentos em um só lugar. Células amarelas e textos azuis são editáveis; células cinzas são calculadas.
B6: Ano-calendário (ano dos rendimentos) | C6: 2026
B8: Navegação
B9: =HYPERLINK("#'Resumo'!A1","Resumo geral") -> Resumo geral | C9: Totais por categoria, pendências e gráfico, atualizados automaticamente.
B10: =HYPERLINK("#'Rendimentos'!A1","Rendimentos") -> Rendimentos | C10: Registre salários, aluguéis, aplicações e o IR retido de cada fonte.
B11: =HYPERLINK("#'Deduções'!A1","Deduções") -> Deduções | C11: Registre despesas dedutíveis (saúde, educação, previdência...) e comprovantes.
B12: =HYPERLINK("#'Bens e Direitos'!A1","Bens e direitos") -> Bens e direitos | C12: Liste bens e saldos em 31/12 do ano anterior e do ano-calendário.
B13: =HYPERLINK("#'Checklist'!A1","Checklist de documentos") -> Checklist de documentos | C13: Acompanhe quais informes e comprovantes já chegaram e foram conferidos.
B14: =HYPERLINK("#'Listas'!A1","Listas de apoio") -> Listas de apoio | C14: Opções dos menus suspensos (tipos, categorias, grupos, status).
B16: Links rápidos
B17: =HYPERLINK("https://www.gov.br/receitafederal/pt-br","Receita Federal") -> Receita Federal | C17: Site oficial: notícias, regras e orientações do Imposto de Renda.
B18: =HYPERLINK("https://www.gov.br/receitafederal/pt-br/assuntos/meu-imposto-de-renda","Meu Imposto de Renda") -> Meu Imposto de Renda | C18: Programas e orientações para preencher e enviar a declaração.
B19: =HYPERLINK("https://cav.receita.fazenda.gov.br/","e-CAC") -> e-CAC | C19: Atendimento virtual: situação fiscal, extrato e pendências.
B20: =HYPERLINK("https://www.gov.br/","Conta gov.br") -> Conta gov.br | C20: Acesso aos serviços digitais do governo federal.
B22: Como usar
B23: 1. Confirme o ano-calendário acima.
B24: 2. Preencha Rendimentos, Deduções e Bens e Direitos (as linhas de exemplo têm valores fictícios: apague-as).
B25: 3. Use o Checklist para marcar cada documento como Pendente, Recebido ou Conferido.
B26: 4. Consulte o Resumo: totais por categoria e quantas pendências ainda existem.
B28: Aviso: esta planilha é uma ferramenta de organização. Ela não substitui o programa oficial da Receita Federal. Regras, limites e prazos mudam a cada ano: confirme sempre no site oficial. Todos os valores de exemplo são fictícios.

Sheet Resumo
B1: RESUMO GERAL
B4: =HYPERLINK("#'Menu'!A1","« Voltar ao Menu") -> « Voltar ao Menu | C4: Ano-calendário: | D4: =ano_base -> 2026
B6: Rendimentos por tipo
B7: Tipo | C7: Valor bruto (R$) | D7: IR retido (R$)
B8: =Listas!B6 -> Salário / trabalho assalariado | C8: =SUMIFS(rend_bruto,rend_tipo,B8) -> 6500 | D8: =SUMIFS(rend_ir,rend_tipo,B8) -> 820.5
B9: =Listas!B7 -> Aluguéis | C9: =SUMIFS(rend_bruto,rend_tipo,B9) -> 2800 | D9: =SUMIFS(rend_ir,rend_tipo,B9) -> 0
B10: =Listas!B8 -> Aplicações financeiras | C10: =SUMIFS(rend_bruto,rend_tipo,B10) -> 1240.3 | D10: =SUMIFS(rend_ir,rend_tipo,B10) -> 186.05
B11: =Listas!B9 -> Dividendos e proventos | C11: =SUMIFS(rend_bruto,rend_tipo,B11) -> 0 | D11: =SUMIFS(rend_ir,rend_tipo,B11) -> 0
B12: =Listas!B10 -> Trabalho autônomo | C12: =SUMIFS(rend_bruto,rend_tipo,B12) -> 0 | D12: =SUMIFS(rend_ir,rend_tipo,B12) -> 0
B13: =Listas!B11 -> Outros rendimentos | C13: =SUMIFS(rend_bruto,rend_tipo,B13) -> 0 | D13: =SUMIFS(rend_ir,rend_tipo,B13) -> 0
B14: Total | C14: =SUM(C8:C13) -> 10540.3 | D14: =SUM(D8:D13) -> 1006.55
B16: Despesas dedutíveis por categoria
B17: Categoria | C17: Valor líquido (R$) | D17: % do total
B18: =Listas!D6 -> Saúde | C18: =SUMIFS(desp_liquido,desp_categoria,B18) -> 650 | D18: =IF($C$23=0,0,C18/$C$23) -> 0.35135135
B19: =Listas!D7 -> Educação | C19: =SUMIFS(desp_liquido,desp_categoria,B19) -> 1200 | D19: =IF($C$23=0,0,C19/$C$23) -> 0.64864865
B20: =Listas!D8 -> Previdência (INSS / PGBL) | C20: =SUMIFS(desp_liquido,desp_categoria,B20) -> 0 | D20: =IF($C$23=0,0,C20/$C$23) -> 0
B21: =Listas!D9 -> Pensão alimentícia | C21: =SUMIFS(desp_liquido,desp_categoria,B21) -> 0 | D21: =IF($C$23=0,0,C21/$C$23) -> 0
B22: =Listas!D10 -> Outras despesas | C22: =SUMIFS(desp_liquido,desp_categoria,B22) -> 0 | D22: =IF($C$23=0,0,C22/$C$23) -> 0
B23: Total | C23: =SUM(C18:C22) -> 1850 | D23: =SUM(D18:D22) -> 1
B25: Bens e direitos por grupo
B26: Grupo | C26: 31/12 ano anterior (R$) | D26: 31/12 ano-calendário (R$)
B27: =Listas!F6 -> Imóveis | C27: =SUMIFS(bens_anterior,bens_grupo,B27) -> 280000 | D27: =SUMIFS(bens_atual,bens_grupo,B27) -> 280000
B28: =Listas!F7 -> Veículos | C28: =SUMIFS(bens_anterior,bens_grupo,B28) -> 45000 | D28: =SUMIFS(bens_atual,bens_grupo,B28) -> 41000
B29: =Listas!F8 -> Aplicações e investimentos | C29: =SUMIFS(bens_anterior,bens_grupo,B29) -> 0 | D29: =SUMIFS(bens_atual,bens_grupo,B29) -> 0
B30: =Listas!F9 -> Depósitos e saldos em conta | C30: =SUMIFS(bens_anterior,bens_grupo,B30) -> 3200 | D30: =SUMIFS(bens_atual,bens_grupo,B30) -> 5100
B31: =Listas!F10 -> Participações societárias | C31: =SUMIFS(bens_anterior,bens_grupo,B31) -> 0 | D31: =SUMIFS(bens_atual,bens_grupo,B31) -> 0
B32: =Listas!F11 -> Outros bens | C32: =SUMIFS(bens_anterior,bens_grupo,B32) -> 0 | D32: =SUMIFS(bens_atual,bens_grupo,B32) -> 0
B33: Total | C33: =SUM(C27:C32) -> 328200 | D33: =SUM(D27:D32) -> 326100
B35: Pendências
B36: Onde | C36: Itens pendentes
B37: Rendimentos | C37: =COUNTIF(rend_situacao,"Pendente") -> 1
B38: Deduções | C38: =COUNTIF(desp_situacao,"Pendente") -> 1
B39: Bens e direitos | C39: =COUNTIF(bens_situacao,"Pendente") -> 1
B40: Documentos ainda não conferidos | C40: =COUNTA(check_docs)-COUNTIF(check_status,"Conferido") -> 10
B41: Checklist conferido (%) | C41: =IF(COUNTA(check_docs)=0,0,COUNTIF(check_status,"Conferido")/COUNTA(check_docs)) -> 0
B42: Situação geral | C42: =IF(SUM(C37:C40)=0,"Tudo conferido","Há pendências") -> Há pendências

Sheet Rendimentos
B1: RENDIMENTOS
B4: =HYPERLINK("#'Menu'!A1","« Voltar ao Menu") -> « Voltar ao Menu | D4: Exemplo nas 3 primeiras linhas (fictício): apague ao usar.
B5: Data | C5: Fonte pagadora | D5: CPF / CNPJ (só números) | E5: Tipo de rendimento | F5: Valor bruto (R$) | G5: IR retido (R$) | H5: Informe recebido? | I5: Situação
B6: 46361 | C6: Empresa Exemplo Ltda | D6: 12345678000190 | E6: Salário / trabalho assalariado | F6: 6500 | G6: 820.5 | H6: Sim | I6: =IF(COUNTA(B6:H6)=0,"",IF(OR(E6="",F6="",H6<>"Sim"),"Pendente","OK")) -> OK
B7: 46203 | C7: Banco Exemplo S.A. | D7: 98765432000110 | E7: Aplicações financeiras | F7: 1240.3 | G7: 186.05 | H7: Sim | I7: =IF(COUNTA(B7:H7)=0,"",IF(OR(E7="",F7="",H7<>"Sim"),"Pendente","OK")) -> OK
B8: 46244 | C8: Locatário Fictício | D8: 12345678901 | E8: Aluguéis | F8: 2800 | G8: 0 | H8: Não | I8: =IF(COUNTA(B8:H8)=0,"",IF(OR(E8="",F8="",H8<>"Sim"),"Pendente","OK")) -> Pendente
I9: =IF(COUNTA(B9:H9)=0,"",IF(OR(E9="",F9="",H9<>"Sim"),"Pendente","OK"))
I10: =IF(COUNTA(B10:H10)=0,"",IF(OR(E10="",F10="",H10<>"Sim"),"Pendente","OK"))
I11: =IF(COUNTA(B11:H11)=0,"",IF(OR(E11="",F11="",H11<>"Sim"),"Pendente","OK"))
I12: =IF(COUNTA(B12:H12)=0,"",IF(OR(E12="",F12="",H12<>"Sim"),"Pendente","OK"))
I13: =IF(COUNTA(B13:H13)=0,"",IF(OR(E13="",F13="",H13<>"Sim"),"Pendente","OK"))
I14: =IF(COUNTA(B14:H14)=0,"",IF(OR(E14="",F14="",H14<>"Sim"),"Pendente","OK"))
I15: =IF(COUNTA(B15:H15)=0,"",IF(OR(E15="",F15="",H15<>"Sim"),"Pendente","OK"))
I16: =IF(COUNTA(B16:H16)=0,"",IF(OR(E16="",F16="",H16<>"Sim"),"Pendente","OK"))
I17: =IF(COUNTA(B17:H17)=0,"",IF(OR(E17="",F17="",H17<>"Sim"),"Pendente","OK"))
I18: =IF(COUNTA(B18:H18)=0,"",IF(OR(E18="",F18="",H18<>"Sim"),"Pendente","OK"))
I19: =IF(COUNTA(B19:H19)=0,"",IF(OR(E19="",F19="",H19<>"Sim"),"Pendente","OK"))
I20: =IF(COUNTA(B20:H20)=0,"",IF(OR(E20="",F20="",H20<>"Sim"),"Pendente","OK"))
... I205: =IF(COUNTA(B205:H205)=0,"",IF(OR(E205="",F205="",H205<>"Sim"),"Pendente","OK"))

Sheet Deduções
B1: DEDUÇÕES (DESPESAS)
B4: =HYPERLINK("#'Menu'!A1","« Voltar ao Menu") -> « Voltar ao Menu | D4: Exemplo nas 3 primeiras linhas (fictício): apague ao usar.
B5: Data | C5: Prestador / beneficiário | D5: CPF / CNPJ (só números) | E5: Categoria | F5: Valor pago (R$) | G5: Reembolso (R$) | H5: Valor líquido (R$) | I5: Comprovante em mãos? | J5: Situação
B6: 46095 | C6: Clínica Exemplo | D6: 11222333000144 | E6: Saúde | F6: 450 | G6: 0 | H6: =IF(F6="","",F6-N(G6)) -> 450 | I6: Sim | J6: =IF(COUNTA(B6:G6,I6)=0,"",IF(OR(E6="",F6="",I6<>"Sim"),"Pendente","OK")) -> OK
B7: 46055 | C7: Escola Exemplo | D7: 55666777000188 | E7: Educação | F7: 1200 | G7: 0 | H7: =IF(F7="","",F7-N(G7)) -> 1200 | I7: Sim | J7: =IF(COUNTA(B7:G7,I7)=0,"",IF(OR(E7="",F7="",I7<>"Sim"),"Pendente","OK")) -> OK
B8: 46274 | C8: Laboratório Fictício | D8: 99888777000166 | E8: Saúde | F8: 320 | G8: 120 | H8: =IF(F8="","",F8-N(G8)) -> 200 | I8: Não | J8: =IF(COUNTA(B8:G8,I8)=0,"",IF(OR(E8="",F8="",I8<>"Sim"),"Pendente","OK")) -> Pendente
H9: =IF(F9="","",F9-N(G9)) | J9: =IF(COUNTA(B9:G9,I9)=0,"",IF(OR(E9="",F9="",I9<>"Sim"),"Pendente","OK"))
H10: =IF(F10="","",F10-N(G10)) | J10: =IF(COUNTA(B10:G10,I10)=0,"",IF(OR(E10="",F10="",I10<>"Sim"),"Pendente","OK"))
H11: =IF(F11="","",F11-N(G11)) | J11: =IF(COUNTA(B11:G11,I11)=0,"",IF(OR(E11="",F11="",I11<>"Sim"),"Pendente","OK"))
H12: =IF(F12="","",F12-N(G12)) | J12: =IF(COUNTA(B12:G12,I12)=0,"",IF(OR(E12="",F12="",I12<>"Sim"),"Pendente","OK"))
H13: =IF(F13="","",F13-N(G13)) | J13: =IF(COUNTA(B13:G13,I13)=0,"",IF(OR(E13="",F13="",I13<>"Sim"),"Pendente","OK"))
H14: =IF(F14="","",F14-N(G14)) | J14: =IF(COUNTA(B14:G14,I14)=0,"",IF(OR(E14="",F14="",I14<>"Sim"),"Pendente","OK"))
H15: =IF(F15="","",F15-N(G15)) | J15: =IF(COUNTA(B15:G15,I15)=0,"",IF(OR(E15="",F15="",I15<>"Sim"),"Pendente","OK"))
H16: =IF(F16="","",F16-N(G16)) | J16: =IF(COUNTA(B16:G16,I16)=0,"",IF(OR(E16="",F16="",I16<>"Sim"),"Pendente","OK"))
H17: =IF(F17="","",F17-N(G17)) | J17: =IF(COUNTA(B17:G17,I17)=0,"",IF(OR(E17="",F17="",I17<>"Sim"),"Pendente","OK"))
H18: =IF(F18="","",F18-N(G18)) | J18: =IF(COUNTA(B18:G18,I18)=0,"",IF(OR(E18="",F18="",I18<>"Sim"),"Pendente","OK"))
H19: =IF(F19="","",F19-N(G19)) | J19: =IF(COUNTA(B19:G19,I19)=0,"",IF(OR(E19="",F19="",I19<>"Sim"),"Pendente","OK"))
H20: =IF(F20="","",F20-N(G20)) | J20: =IF(COUNTA(B20:G20,I20)=0,"",IF(OR(E20="",F20="",I20<>"Sim"),"Pendente","OK"))
... H205: =IF(F205="","",F205-N(G205)) | J205: =IF(COUNTA(B205:G205,I205)=0,"",IF(OR(E205="",F205="",I205<>"Sim"),"Pendente","OK"))

Sheet Bens e Direitos
B1: BENS E DIREITOS
B4: =HYPERLINK("#'Menu'!A1","« Voltar ao Menu") -> « Voltar ao Menu | D4: Exemplo nas 3 primeiras linhas (fictício): apague ao usar.
B5: Descrição | C5: Grupo | D5: Valor em 31/12 do ano anterior (R$) | E5: Valor em 31/12 do ano-calendário (R$) | F5: Variação (R$) | G5: Observações | H5: Documento em mãos? | I5: Situação
B6: Apartamento exemplo (financiado) | C6: Imóveis | D6: 280000 | E6: 280000 | F6: =IF(COUNTA(D6:E6)=0,"",N(E6)-N(D6)) -> 0 | H6: Sim | I6: =IF(COUNTA(B6:E6,G6:H6)=0,"",IF(OR(C6="",E6="",H6<>"Sim"),"Pendente","OK")) -> OK
B7: Carro exemplo | C7: Veículos | D7: 45000 | E7: 41000 | F7: =IF(COUNTA(D7:E7)=0,"",N(E7)-N(D7)) -> -4000 | H7: Sim | I7: =IF(COUNTA(B7:E7,G7:H7)=0,"",IF(OR(C7="",E7="",H7<>"Sim"),"Pendente","OK")) -> OK
B8: Conta corrente Banco Exemplo | C8: Depósitos e saldos em conta | D8: 3200 | E8: 5100 | F8: =IF(COUNTA(D8:E8)=0,"",N(E8)-N(D8)) -> 1900 | H8: Não | I8: =IF(COUNTA(B8:E8,G8:H8)=0,"",IF(OR(C8="",E8="",H8<>"Sim"),"Pendente","OK")) -> Pendente
F9: =IF(COUNTA(D9:E9)=0,"",N(E9)-N(D9)) | I9: =IF(COUNTA(B9:E9,G9:H9)=0,"",IF(OR(C9="",E9="",H9<>"Sim"),"Pendente","OK"))
F10: =IF(COUNTA(D10:E10)=0,"",N(E10)-N(D10)) | I10: =IF(COUNTA(B10:E10,G10:H10)=0,"",IF(OR(C10="",E10="",H10<>"Sim"),"Pendente","OK"))
F11: =IF(COUNTA(D11:E11)=0,"",N(E11)-N(D11)) | I11: =IF(COUNTA(B11:E11,G11:H11)=0,"",IF(OR(C11="",E11="",H11<>"Sim"),"Pendente","OK"))
F12: =IF(COUNTA(D12:E12)=0,"",N(E12)-N(D12)) | I12: =IF(COUNTA(B12:E12,G12:H12)=0,"",IF(OR(C12="",E12="",H12<>"Sim"),"Pendente","OK"))
F13: =IF(COUNTA(D13:E13)=0,"",N(E13)-N(D13)) | I13: =IF(COUNTA(B13:E13,G13:H13)=0,"",IF(OR(C13="",E13="",H13<>"Sim"),"Pendente","OK"))
F14: =IF(COUNTA(D14:E14)=0,"",N(E14)-N(D14)) | I14: =IF(COUNTA(B14:E14,G14:H14)=0,"",IF(OR(C14="",E14="",H14<>"Sim"),"Pendente","OK"))
F15: =IF(COUNTA(D15:E15)=0,"",N(E15)-N(D15)) | I15: =IF(COUNTA(B15:E15,G15:H15)=0,"",IF(OR(C15="",E15="",H15<>"Sim"),"Pendente","OK"))
F16: =IF(COUNTA(D16:E16)=0,"",N(E16)-N(D16)) | I16: =IF(COUNTA(B16:E16,G16:H16)=0,"",IF(OR(C16="",E16="",H16<>"Sim"),"Pendente","OK"))
F17: =IF(COUNTA(D17:E17)=0,"",N(E17)-N(D17)) | I17: =IF(COUNTA(B17:E17,G17:H17)=0,"",IF(OR(C17="",E17="",H17<>"Sim"),"Pendente","OK"))
F18: =IF(COUNTA(D18:E18)=0,"",N(E18)-N(D18)) | I18: =IF(COUNTA(B18:E18,G18:H18)=0,"",IF(OR(C18="",E18="",H18<>"Sim"),"Pendente","OK"))
F19: =IF(COUNTA(D19:E19)=0,"",N(E19)-N(D19)) | I19: =IF(COUNTA(B19:E19,G19:H19)=0,"",IF(OR(C19="",E19="",H19<>"Sim"),"Pendente","OK"))
F20: =IF(COUNTA(D20:E20)=0,"",N(E20)-N(D20)) | I20: =IF(COUNTA(B20:E20,G20:H20)=0,"",IF(OR(C20="",E20="",H20<>"Sim"),"Pendente","OK"))
... F205: =IF(COUNTA(D205:E205)=0,"",N(E205)-N(D205)) | I205: =IF(COUNTA(B205:E205,G205:H205)=0,"",IF(OR(C205="",E205="",H205<>"Sim"),"Pendente","OK"))

Sheet Checklist
B1: CHECKLIST DE DOCUMENTOS
B4: =HYPERLINK("#'Menu'!A1","« Voltar ao Menu") -> « Voltar ao Menu | D4: Os 10 documentos são sugestões: edite à vontade.
B5: Documento | C5: Origem | D5: Status | E5: Observações
B6: Informe de rendimentos do empregador | C6: Empresa / RH | D6: Pendente
B7: Informe de rendimentos bancários | C7: Bancos | D7: Pendente
B8: Informe de corretora / investimentos | C8: Corretoras | D8: Pendente
B9: Recibos e comprovantes de saúde | C9: Médicos, clínicas, planos | D9: Pendente
B10: Comprovantes de educação | C10: Escolas e faculdades | D10: Pendente
B11: Extrato de previdência privada | C11: Seguradora / banco | D11: Pendente
B12: Documentos de imóveis | C12: Cartório / construtora | D12: Pendente
B13: Documentos de veículos | C13: Detran / concessionária | D13: Pendente
B14: Informações de dependentes (CPF, datas) | C14: Documentos pessoais | D14: Pendente
B15: Declaração do ano anterior e recibo | C15: Arquivo pessoal | D15: Pendente

Sheet Listas
B1: Listas de apoio
B4: =HYPERLINK("#'Menu'!A1","« Voltar ao Menu") -> « Voltar ao Menu
B5: Tipos de rendimento | D5: Categorias de despesa | F5: Grupos de bens | H5: Status do documento | J5: Sim / Não
B6: Salário / trabalho assalariado | D6: Saúde | F6: Imóveis | H6: Pendente | J6: Sim
B7: Aluguéis | D7: Educação | F7: Veículos | H7: Recebido | J7: Não
B8: Aplicações financeiras | D8: Previdência (INSS / PGBL) | F8: Aplicações e investimentos | H8: Conferido
B9: Dividendos e proventos | D9: Pensão alimentícia | F9: Depósitos e saldos em conta
B10: Trabalho autônomo | D10: Outras despesas | F10: Participações societárias
B11: Outros rendimentos | F11: Outros bens
B14: Para incluir uma opção nova, edite o texto de uma linha existente. As listas alimentam os menus suspensos e os totais do Resumo.
