Workbook

Sheet Menu
B1: Agregador de Dados — Declaração de Imposto de Renda
B3: Escolha uma seção para navegar. Em cada aba, use o link “← Voltar ao Menu”.
B5: 1 Dados do contribuinte | E5: Nome, CPF, ano-base e dependentes
B7: 2 Rendimentos | E7: Fontes pagadoras e valores recebidos
B9: 3 Deduções e despesas | E9: Saúde, educação, previdência e outras
B11: 4 Bens e direitos | E11: Patrimônio em 31/12 do ano anterior e atual
B13: 5 Resumo | E13: Totais consolidados por categoria
B15: 6 Links rápidos | E15: Sites oficiais da Receita e do gov.br
B17: 7 Listas de apoio | E17: Opções usadas nas listas suspensas
B20: Legenda: células amarelas com texto azul = campos para preencher. Células cinzas/pretas = fórmulas (não editar).
B21: As linhas de exemplo (ex.: “Empresa Exemplo Ltda”) devem ser apagadas ou substituídas pelos seus dados.

Sheet Contribuinte
A1: Dados do contribuinte | F1: ← Voltar ao Menu
A3: Nome completo | B3: Maria da Silva (exemplo)
A4: CPF (somente números) | B4: 12345678909
A5: Ano-base | B5: 2025
A6: Ano do exercício | B6: =B5+1 -> 2026
A7: Número de dependentes | B7: 1
A8: E-mail | B8: maria@exemplo.com
A10: Ano do exercício = ano-base + 1 (fórmula). O ano-base alimenta as validações de data nas outras abas.

Sheet Rendimentos
A1: Rendimentos recebidos | H1: ← Voltar ao Menu
D2: Total: | E2: =SUM(D4:D103) -> 60000
A3: Fonte pagadora | B3: CNPJ / CPF (números) | C3: Tipo de rendimento | D3: Valor anual (R$) | E3: IR retido na fonte (R$) | F3: Situação do documento
A4: Empresa Exemplo Ltda | B4: 12345678000195 | C4: Tributável - Trabalho assalariado | D4: 60000 | E4: 4500 | F4: Pendente
A104: Aviso: linha laranja = valor informado sem fonte pagadora ou sem tipo. A linha 4 é um exemplo — substitua ou apague.

Sheet Deducoes
A1: Deduções e despesas | H1: ← Voltar ao Menu
D2: Total: | E2: =SUM(E4:E103) -> 350
A3: Descrição / beneficiário | B3: CPF / CNPJ do prestador | C3: Categoria | D3: Data do pagamento | E3: Valor (R$) | F3: Situação do documento
A4: Consulta médica (exemplo) | B4: 12345678909 | C4: Saúde | D4: =DATE(Contribuinte!$B$5,3,15) -> 45731 | E4: 350 | F4: Documento em mãos
A104: Aviso: linha laranja = valor sem descrição ou sem categoria. A linha 4 é um exemplo — substitua ou apague.

Sheet Bens_Direitos
A1: Bens e direitos | H1: ← Voltar ao Menu
B2: Totais: | C2: =SUM(C4:C103) -> 2000 | D2: =SUM(D4:D103) -> 3500 | E2: =D2-C2 -> 1500
A3: Descrição do bem | B3: Tipo | C3: Situação em 31/12 do ano anterior (R$) | D3: Situação em 31/12 do ano-base (R$) | E3: Variação (R$) | F3: Situação do documento
A4: Conta corrente Banco Exemplo | B4: Conta bancária | C4: 2000 | D4: 3500 | E4: =IF(AND(C4="",D4=""),"",D4-C4) -> 1500 | F4: Pendente
E5: =IF(AND(C5="",D5=""),"",D5-C5)
E6: =IF(AND(C6="",D6=""),"",D6-C6)
E7: =IF(AND(C7="",D7=""),"",D7-C7)
E8: =IF(AND(C8="",D8=""),"",D8-C8)
E9: =IF(AND(C9="",D9=""),"",D9-C9)
E10: =IF(AND(C10="",D10=""),"",D10-C10)
E11: =IF(AND(C11="",D11=""),"",D11-C11)
E12: =IF(AND(C12="",D12=""),"",D12-C12)
E13: =IF(AND(C13="",D13=""),"",D13-C13)
E14: =IF(AND(C14="",D14=""),"",D14-C14)
E15: =IF(AND(C15="",D15=""),"",D15-C15)
E16: =IF(AND(C16="",D16=""),"",D16-C16)
... E103: =IF(AND(C103="",D103=""),"",D103-C103)
A104: A coluna Variação é fórmula (não editar). A linha 4 é um exemplo — substitua ou apague.

Sheet Resumo
A1: Resumo consolidado | E1: ← Voltar ao Menu
A3: Contribuinte: | B3: =Contribuinte!B3 -> Maria da Silva (exemplo)
A4: Ano-base / Exercício: | B4: =Contribuinte!B5&" / "&Contribuinte!B6 -> 2025 / 2026
A6: Rendimentos por tipo | B6: Total (R$) | C6: Nº de lançamentos
A7: Tributável - Trabalho assalariado | B7: =SUMIFS(Rendimentos!$D$4:$D$103,Rendimentos!$C$4:$C$103,A7) -> 60000 | C7: =COUNTIFS(Rendimentos!$C$4:$C$103,A7) -> 1
A8: Tributável - Autônomo / PJ | B8: =SUMIFS(Rendimentos!$D$4:$D$103,Rendimentos!$C$4:$C$103,A8) -> 0 | C8: =COUNTIFS(Rendimentos!$C$4:$C$103,A8) -> 0
A9: Tributável - Aluguéis | B9: =SUMIFS(Rendimentos!$D$4:$D$103,Rendimentos!$C$4:$C$103,A9) -> 0 | C9: =COUNTIFS(Rendimentos!$C$4:$C$103,A9) -> 0
A10: Isento / Não tributável | B10: =SUMIFS(Rendimentos!$D$4:$D$103,Rendimentos!$C$4:$C$103,A10) -> 0 | C10: =COUNTIFS(Rendimentos!$C$4:$C$103,A10) -> 0
A11: Tributação exclusiva na fonte | B11: =SUMIFS(Rendimentos!$D$4:$D$103,Rendimentos!$C$4:$C$103,A11) -> 0 | C11: =COUNTIFS(Rendimentos!$C$4:$C$103,A11) -> 0
A12: Total | B12: =SUM(B7:B11) -> 60000 | C12: =SUM(C7:C11) -> 1
A14: Deduções por categoria | B14: Total (R$) | C14: Nº de lançamentos
A15: Saúde | B15: =SUMIFS(Deducoes!$E$4:$E$103,Deducoes!$C$4:$C$103,A15) -> 350 | C15: =COUNTIFS(Deducoes!$C$4:$C$103,A15) -> 1
A16: Educação | B16: =SUMIFS(Deducoes!$E$4:$E$103,Deducoes!$C$4:$C$103,A16) -> 0 | C16: =COUNTIFS(Deducoes!$C$4:$C$103,A16) -> 0
A17: Previdência oficial / privada | B17: =SUMIFS(Deducoes!$E$4:$E$103,Deducoes!$C$4:$C$103,A17) -> 0 | C17: =COUNTIFS(Deducoes!$C$4:$C$103,A17) -> 0
A18: Pensão alimentícia | B18: =SUMIFS(Deducoes!$E$4:$E$103,Deducoes!$C$4:$C$103,A18) -> 0 | C18: =COUNTIFS(Deducoes!$C$4:$C$103,A18) -> 0
A19: Dependentes | B19: =SUMIFS(Deducoes!$E$4:$E$103,Deducoes!$C$4:$C$103,A19) -> 0 | C19: =COUNTIFS(Deducoes!$C$4:$C$103,A19) -> 0
A20: Livro-caixa | B20: =SUMIFS(Deducoes!$E$4:$E$103,Deducoes!$C$4:$C$103,A20) -> 0 | C20: =COUNTIFS(Deducoes!$C$4:$C$103,A20) -> 0
A21: Total | B21: =SUM(B15:B20) -> 350 | C21: =SUM(C15:C20) -> 1
A23: Bens e direitos por tipo (31/12 do ano-base) | B23: Total (R$) | C23: Nº de lançamentos
A24: Imóvel | B24: =SUMIFS(Bens_Direitos!$D$4:$D$103,Bens_Direitos!$B$4:$B$103,A24) -> 0 | C24: =COUNTIFS(Bens_Direitos!$B$4:$B$103,A24) -> 0
A25: Veículo | B25: =SUMIFS(Bens_Direitos!$D$4:$D$103,Bens_Direitos!$B$4:$B$103,A25) -> 0 | C25: =COUNTIFS(Bens_Direitos!$B$4:$B$103,A25) -> 0
A26: Conta bancária | B26: =SUMIFS(Bens_Direitos!$D$4:$D$103,Bens_Direitos!$B$4:$B$103,A26) -> 3500 | C26: =COUNTIFS(Bens_Direitos!$B$4:$B$103,A26) -> 1
A27: Aplicação financeira | B27: =SUMIFS(Bens_Direitos!$D$4:$D$103,Bens_Direitos!$B$4:$B$103,A27) -> 0 | C27: =COUNTIFS(Bens_Direitos!$B$4:$B$103,A27) -> 0
A28: Ações / FIIs | B28: =SUMIFS(Bens_Direitos!$D$4:$D$103,Bens_Direitos!$B$4:$B$103,A28) -> 0 | C28: =COUNTIFS(Bens_Direitos!$B$4:$B$103,A28) -> 0
A29: Outros | B29: =SUMIFS(Bens_Direitos!$D$4:$D$103,Bens_Direitos!$B$4:$B$103,A29) -> 0 | C29: =COUNTIFS(Bens_Direitos!$B$4:$B$103,A29) -> 0
A30: Total | B30: =SUM(B24:B29) -> 3500 | C30: =SUM(C24:C29) -> 1
A32: Indicadores | B32: Valor (R$)
A33: Rendimentos tributáveis (3 primeiros tipos) | B33: =SUM(B7:B9) -> 60000
A34: Total de deduções | B34: =B21 -> 350
A35: Base de cálculo simplificada (tributáveis − deduções) | B35: =MAX(0,B33-B34) -> 59650
A36: IR retido na fonte (total) | B36: =SUM(Rendimentos!E4:E103) -> 4500
A38: Atenção: a base é uma estimativa organizacional. O cálculo oficial (tabela progressiva, limites de dedução, desconto simplificado) é feito no programa da Receita Federal.
A39: Aba Rendimentos: somente os tipos tributáveis entram na base; isentos e exclusivos na fonte são informados à parte na declaração.

Sheet Links
A1: Links rápidos | E1: ← Voltar ao Menu
A3: Recurso | B3: Descrição | C3: Endereço
A4: Meu Imposto de Renda (Receita Federal) | B4: Página oficial com programa e orientações | C4: https://www.gov.br/receitafederal/pt-br/assuntos/meu-imposto-de-renda
A5: Portal gov.br | B5: Acesso à conta gov.br | C5: https://www.gov.br
A6: Centro Virtual de Atendimento (e-CAC) | B6: Extrato, pendências e serviços da Receita | C6: https://cav.receita.fazenda.gov.br/
A7: Consulta de situação cadastral do CPF | B7: Verifica regularidade do CPF | C7: https://servicos.receita.fazenda.gov.br/servicos/cpf/consultasituacao/consultapublica.asp
A9: Confira se os endereços continuam válidos antes de usar; os portais do governo mudam com frequência.

Sheet Listas
A1: Listas de apoio (usadas nas validações) | F1: ← Voltar ao Menu
A3: Tipos de rendimento | B3: Categorias de dedução | C3: Tipos de bem | D3: Situação
A4: Tributável - Trabalho assalariado | B4: Saúde | C4: Imóvel | D4: Pendente
A5: Tributável - Autônomo / PJ | B5: Educação | C5: Veículo | D5: Documento em mãos
A6: Tributável - Aluguéis | B6: Previdência oficial / privada | C6: Conta bancária | D6: Conferido
A7: Isento / Não tributável | B7: Pensão alimentícia | C7: Aplicação financeira
A8: Tributação exclusiva na fonte | B8: Dependentes | C8: Ações / FIIs
B9: Livro-caixa | C9: Outros
A13: Para incluir novas opções, escreva abaixo da última linha de cada lista e ajuste o intervalo nomeado em Fórmulas > Gerenciador de Nomes.
